[{"type": "function", "name": "uniswapV3SwapCallback", "inputs": [{"name": "amount0Delta", "type": "int256", "internalType": "int256"}, {"name": "amount1Delta", "type": "int256", "internalType": "int256"}, {"name": "data", "type": "bytes", "internalType": "bytes"}], "outputs": [], "stateMutability": "nonpayable"}, {"type": "error", "name": "RouterAdapter__InsufficientLBLiquidity", "inputs": []}, {"type": "error", "name": "RouterAdapter__InsufficientTMLiquidity", "inputs": []}, {"type": "error", "name": "RouterAdapter__InvalidId", "inputs": []}, {"type": "error", "name": "RouterAdapter__UnexpectedAmountIn", "inputs": []}, {"type": "error", "name": "RouterAdapter__UnexpectedCallback", "inputs": []}, {"type": "error", "name": "RouterAdapter__UniswapV3SwapCallbackOnly", "inputs": [{"name": "amount0Delta", "type": "int256", "internalType": "int256"}, {"name": "amount1Delta", "type": "int256", "internalType": "int256"}]}, {"type": "error", "name": "TokenLib__TransferFailed", "inputs": []}]